SimpleWallet-1.0.0.data/data/simplewallet/config/config.json
simplewallet/__init__.py
simplewallet/__main__.py
simplewallet/main.py
simplewallet/simplewallet.py
simplewallet/bitcoin/__init__.py
simplewallet/bitcoin/address.py
simplewallet/bitcoin/helper.py
simplewallet/bitcoin/privkey.py
simplewallet/bitcoin/pubkey.py
simplewallet/bitcoin/signer.py
simplewallet/bitcoin/verifier.py
simplewallet/crypto/__init__.py
simplewallet/crypto/base.py
simplewallet/crypto/bech32.py
simplewallet/crypto/ecdsa.py
simplewallet/crypto/hash160.py
simplewallet/crypto/ripemd.py
simplewallet/crypto/sha256.py
simplewallet/dircrawler/__init__.py
simplewallet/dircrawler/crawler.py
simplewallet/dircrawler/datamodder.py
simplewallet/dircrawler/filemodder.py
simplewallet/gui/__init__.py
simplewallet/gui/addressgui.py
simplewallet/gui/instance.py
simplewallet/gui/signergui.py
simplewallet/gui/verifiergui.py
simplewallet/utils/__init__.py
simplewallet/utils/commoncmd.py
simplewallet/utils/configloader.py
simplewallet/utils/conversion.py
simplewallet/utils/hexxer.py
SimpleWallet-1.0.0.dist-info/LICENSE
SimpleWallet-1.0.0.dist-info/METADATA
SimpleWallet-1.0.0.dist-info/WHEEL
SimpleWallet-1.0.0.dist-info/entry_points.txt
SimpleWallet-1.0.0.dist-info/top_level.txt
SimpleWallet-1.0.0.dist-info/RECORD
