Metadata-Version: 2.1
Name: SimpleWallet
Version: 1.0.0
Summary: Simple wallet for Bitcoin.
Home-page: https://github.com/ArcticTechnology/SimpleWallet
Author: ArcticTechnology
Author-email: arctic.technology.mail@gmail.com
License: MIT
Keywords: bitcoin,crypto,wallet
Classifier: Development Status :: 4 - Beta
Classifier: License :: OSI Approved :: MIT License
Classifier: Natural Language :: English
Classifier: Operating System :: OS Independent
Classifier: Programming Language :: Python
Classifier: Programming Language :: Python :: 3
Classifier: Programming Language :: Python :: 3 :: Only
Classifier: Programming Language :: Python :: 3.8
Classifier: Programming Language :: Python :: 3.9
Classifier: Intended Audience :: Developers
Classifier: Intended Audience :: Science/Research
Classifier: Intended Audience :: Information Technology
Classifier: Intended Audience :: Financial and Insurance Industry
Classifier: Topic :: Education
Classifier: Topic :: Software Development
Classifier: Topic :: Software Development :: Libraries
Requires-Python: >=3.8
License-File: LICENSE
Requires-Dist: libsecp256k1-0 (>=0.3.0)
